naszilla/__init__.py
naszilla/acquisition_functions.py
naszilla/meta_neural_net.py
naszilla/nas_algorithms.py
naszilla/nas_benchmarks.py
naszilla/params.py
naszilla/run_experiments.py
naszilla/bo/__init__.py
naszilla/bo/acq/__init__.py
naszilla/bo/acq/acqmap.py
naszilla/bo/acq/acqopt.py
naszilla/bo/acq/acquisition.py
naszilla/bo/bo/__init__.py
naszilla/bo/bo/probo.py
naszilla/bo/dom/__init__.py
naszilla/bo/dom/list.py
naszilla/bo/dom/real.py
naszilla/bo/ds/__init__.py
naszilla/bo/ds/makept.py
naszilla/bo/fn/__init__.py
naszilla/bo/fn/functionhandler.py
naszilla/bo/pp/__init__.py
naszilla/bo/pp/pp_core.py
naszilla/bo/pp/pp_gp_george.py
naszilla/bo/pp/pp_gp_my_distmat.py
naszilla/bo/pp/pp_gp_stan.py
naszilla/bo/pp/pp_gp_stan_distmat.py
naszilla/bo/pp/gp/__init__.py
naszilla/bo/pp/gp/gp_utils.py
naszilla/bo/pp/stan/__init__.py
naszilla/bo/pp/stan/compile_stan.py
naszilla/bo/pp/stan/gp_distmat.py
naszilla/bo/pp/stan/gp_distmat_fixedsig.py
naszilla/bo/pp/stan/gp_hier2.py
naszilla/bo/pp/stan/gp_hier2_matern.py
naszilla/bo/pp/stan/gp_hier3.py
naszilla/bo/util/__init__.py
naszilla/bo/util/datatransform.py
naszilla/bo/util/print_utils.py
naszilla/gcn/__init__.py
naszilla/gcn/dataset.py
naszilla/gcn/model.py
naszilla/gcn/train_gcn.py
naszilla/gcn/utils.py
naszilla/nas_bench_101/__init__.py
naszilla/nas_bench_101/cell_101.py
naszilla/nas_bench_101/distances.py
naszilla/nas_bench_101/encodings.py
naszilla/nas_bench_101/mutations.py
naszilla/nas_bench_101/sample_random.py
naszilla/nas_bench_201/__init__.py
naszilla/nas_bench_201/cell_201.py
naszilla/nas_bench_201/distances.py
naszilla/nas_bench_301/__init__.py
naszilla/nas_bench_301/cell_301.py
naszilla-1.0.dist-info/LICENSE
naszilla-1.0.dist-info/METADATA
naszilla-1.0.dist-info/WHEEL
naszilla-1.0.dist-info/top_level.txt
naszilla-1.0.dist-info/RECORD
